django_easy_quiz/__init__.py
django_easy_quiz/admin.py
django_easy_quiz/apps.py
django_easy_quiz/cms_plugins.py
django_easy_quiz/forms.py
django_easy_quiz/locale/fr/LC_MESSAGES/django.mo
django_easy_quiz/locale/fr/LC_MESSAGES/django.po
django_easy_quiz/migrations/0001_initial.py
django_easy_quiz/migrations/0002_auto_20230929_1725.py
django_easy_quiz/migrations/0003_auto_20231003_1729.py
django_easy_quiz/migrations/0004_auto_20231009_1707.py
django_easy_quiz/migrations/0005_savedquiz_interpretation_max_symbol_and_more.py
django_easy_quiz/migrations/0006_weightedanswersquiz_show_score_summary.py
django_easy_quiz/migrations/0007_auto_20240624_1144.py
django_easy_quiz/migrations/0008_auto_20250707_1029.py
django_easy_quiz/migrations/0009_moreinfoquestion_is_required.py
django_easy_quiz/migrations/__init__.py
django_easy_quiz/models.py
django_easy_quiz/settings.py
django_easy_quiz/templates/django_easy_quiz/interpretation_form.html
django_easy_quiz/templates/django_easy_quiz/interpretation_plugin.html
django_easy_quiz/templates/django_easy_quiz/more_info_quiz.html
django_easy_quiz/templates/django_easy_quiz/quiz_pdf.html
django_easy_quiz/templates/django_easy_quiz/weighted_answers_form.html
django_easy_quiz/templates/django_easy_quiz/weighted_answers_plugin.html
django_easy_quiz/urls.py
django_easy_quiz/utils.py
django_easy_quiz/views/interpretation.py
django_easy_quiz/views/misc.py
django_easy_quiz/views/weightedanswers.py
django_easy_quiz-6.5.2.dist-info/LICENSE
django_easy_quiz-6.5.2.dist-info/METADATA
django_easy_quiz-6.5.2.dist-info/WHEEL
django_easy_quiz-6.5.2.dist-info/RECORD
