Metadata-Version: 2.3
Name: django-easy-quiz
Version: 6.5.2
Summary: Create weighted answers or interpretation quizzes with ease!
License: GNU GPLv3
Author: Kapt dev team
Author-email: dev@kapt.mobi
Requires-Python: >=3.8
Classifier: License :: Other/Proprietary License
Classifier: Programming Language :: Python :: 3
Classifier: Programming Language :: Python :: 3.8
Classifier: Programming Language :: Python :: 3.9
Classifier: Programming Language :: Python :: 3.10
Classifier: Programming Language :: Python :: 3.11
Classifier: Programming Language :: Python :: 3.12
Classifier: Programming Language :: Python :: 3.13
Requires-Dist: Django (>2.2)
Requires-Dist: django-ckeditor
Requires-Dist: django-ckeditor-filebrowser-filer (==0.5.*)
Requires-Dist: django-import-export (==3.*)
Requires-Dist: weasyprint (==52.*)
Project-URL: Repository, https://gitlab.com/kapt/open-source/django-easy-quiz
